ZhihuWendaWeiHuaweiGongzuoJinianZhihouHuaweiHuiXiemoshalvShiZhendeMa/README.md
ZhihuWendaWeiHuaweiGongzuoJinianZhihouHuaweiHuiXiemoshalvShiZhendeMa/__init__.py
ZhihuWendaWeiHuaweiGongzuoJinianZhihouHuaweiHuiXiemoshalvShiZhendeMa/__main__.py
ZhihuWendaWeiHuaweiGongzuoJinianZhihouHuaweiHuiXiemoshalvShiZhendeMa/file.epub
ZhihuWendaWeiHuaweiGongzuoJinianZhihouHuaweiHuiXiemoshalvShiZhendeMa/index.html
ZhihuWendaWeiHuaweiGongzuoJinianZhihouHuaweiHuiXiemoshalvShiZhendeMa/css/__init__.py
ZhihuWendaWeiHuaweiGongzuoJinianZhihouHuaweiHuiXiemoshalvShiZhendeMa/css/annotations.css
ZhihuWendaWeiHuaweiGongzuoJinianZhihouHuaweiHuiXiemoshalvShiZhendeMa/css/main.css
ZhihuWendaWeiHuaweiGongzuoJinianZhihouHuaweiHuiXiemoshalvShiZhendeMa/css/normalize.css
ZhihuWendaWeiHuaweiGongzuoJinianZhihouHuaweiHuiXiemoshalvShiZhendeMa/css/popup.css
ZhihuWendaWeiHuaweiGongzuoJinianZhihouHuaweiHuiXiemoshalvShiZhendeMa/font/__init__.py
ZhihuWendaWeiHuaweiGongzuoJinianZhihouHuaweiHuiXiemoshalvShiZhendeMa/font/fontello.eot
ZhihuWendaWeiHuaweiGongzuoJinianZhihouHuaweiHuiXiemoshalvShiZhendeMa/font/fontello.svg
ZhihuWendaWeiHuaweiGongzuoJinianZhihouHuaweiHuiXiemoshalvShiZhendeMa/font/fontello.ttf
ZhihuWendaWeiHuaweiGongzuoJinianZhihouHuaweiHuiXiemoshalvShiZhendeMa/font/fontello.woff
ZhihuWendaWeiHuaweiGongzuoJinianZhihouHuaweiHuiXiemoshalvShiZhendeMa/img/__init__.py
ZhihuWendaWeiHuaweiGongzuoJinianZhihouHuaweiHuiXiemoshalvShiZhendeMa/img/annotator-glyph-sprite.png
ZhihuWendaWeiHuaweiGongzuoJinianZhihouHuaweiHuiXiemoshalvShiZhendeMa/img/annotator-icon-sprite.png
ZhihuWendaWeiHuaweiGongzuoJinianZhihouHuaweiHuiXiemoshalvShiZhendeMa/img/apple-touch-icon.png
ZhihuWendaWeiHuaweiGongzuoJinianZhihouHuaweiHuiXiemoshalvShiZhendeMa/img/cancelfullscreen.png
ZhihuWendaWeiHuaweiGongzuoJinianZhihouHuaweiHuiXiemoshalvShiZhendeMa/img/close.png
ZhihuWendaWeiHuaweiGongzuoJinianZhihouHuaweiHuiXiemoshalvShiZhendeMa/img/fullscreen.png
ZhihuWendaWeiHuaweiGongzuoJinianZhihouHuaweiHuiXiemoshalvShiZhendeMa/img/loader.gif
zhihu_wenda_wei_huawei_gongzuo_jinian_zhihou_huawei_hui_xiemoshalv_shi_zhende_ma-2024.3.5.0.dist-info/METADATA
zhihu_wenda_wei_huawei_gongzuo_jinian_zhihou_huawei_hui_xiemoshalv_shi_zhende_ma-2024.3.5.0.dist-info/WHEEL
zhihu_wenda_wei_huawei_gongzuo_jinian_zhihou_huawei_hui_xiemoshalv_shi_zhende_ma-2024.3.5.0.dist-info/entry_points.txt
zhihu_wenda_wei_huawei_gongzuo_jinian_zhihou_huawei_hui_xiemoshalv_shi_zhende_ma-2024.3.5.0.dist-info/top_level.txt
zhihu_wenda_wei_huawei_gongzuo_jinian_zhihou_huawei_hui_xiemoshalv_shi_zhende_ma-2024.3.5.0.dist-info/RECORD
